stocktrading/__init__.py
stocktrading/bot.py
stocktrading/main.py
stocktrading/run.py
stocktrading/utils/indicators/__init__.py
stocktrading/utils/indicators/base.py
stocktrading-0.1.5.dist-info/METADATA
stocktrading-0.1.5.dist-info/WHEEL
stocktrading-0.1.5.dist-info/top_level.txt
stocktrading-0.1.5.dist-info/RECORD
