Metadata-Version: 2.4
Name: stocktrading
Version: 0.1.5
Summary: Nothing to describe
Author-email: Tran Quoc Dat <dat.tq6141@gmail.com>
License-Expression: MIT
Project-URL: Homepage, https://github.com/boitrann/stocktrading
Project-URL: Source, https://github.com/boitrann/stocktrading
Keywords: finance,stock,telegram
Classifier: Programming Language :: Python :: 3
Classifier: Operating System :: OS Independent
Requires-Python: >=3.10
Requires-Dist: metastock2pd==1.0.2
Requires-Dist: mplfinance
Requires-Dist: TA-Lib==0.6.7
Requires-Dist: loguru==0.7.3
Requires-Dist: python-telegram-bot==22.3
Requires-Dist: dotenv
